MANIFEST.in
README.md
setup.py
pepdata/__init__.py
pepdata/amino_acid.py
pepdata/amino_acid_alphabet.py
pepdata/amino_acid_properties.py
pepdata/blosum.py
pepdata/chou_fasman.py
pepdata/common.py
pepdata/peptide_vectorizer.py
pepdata/pmbec.py
pepdata/reduced_alphabet.py
pepdata/residue_contact_energies.py
pepdata/static_data.py
pepdata.egg-info/PKG-INFO
pepdata.egg-info/SOURCES.txt
pepdata.egg-info/dependency_links.txt
pepdata.egg-info/requires.txt
pepdata.egg-info/top_level.txt
pepdata/iedb/__init__.py
pepdata/iedb/alleles.py
pepdata/iedb/common.py
pepdata/iedb/memoize.py
pepdata/iedb/mhc.py
pepdata/iedb/tcell.py
pepdata/matrices/BLOSUM30
pepdata/matrices/BLOSUM50
pepdata/matrices/BLOSUM62
pepdata/matrices/__init__.py
pepdata/matrices/amino_acid_properties.txt
pepdata/matrices/helix_vs_coil.txt
pepdata/matrices/helix_vs_strand.txt
pepdata/matrices/pmbec.mat
pepdata/matrices/strand_vs_coil.txt
test/test_amino_acids.py
test/test_blosum.py
test/test_iedb_alleles.py
test/test_iedb_mhc.py
test/test_iedb_tcell.py
test/test_ngram.py
test/test_pmbec.py